{"nodes": [{"id": "c_users_myself_desktop_projects_hareesh_portfolio_1_src_components_space_helpoverlay_tsx", "label": "HelpOverlay.tsx", "file_type": "code", "source_file": "C:\\Users\\myself\\Desktop\\Projects\\hareesh-portfolio-1\\src\\components\\space\\HelpOverlay.tsx", "source_location": "L1"}, {"id": "helpoverlay_helpoverlay", "label": "HelpOverlay()", "file_type": "code", "source_file": "C:\\Users\\myself\\Desktop\\Projects\\hareesh-portfolio-1\\src\\components\\space\\HelpOverlay.tsx", "source_location": "L19"}], "edges": [{"source": "c_users_myself_desktop_projects_hareesh_portfolio_1_src_components_space_helpoverlay_tsx", "target": "react", "relation": "imports_from", "confidence": "EXTRACTED", "source_file": "C:\\Users\\myself\\Desktop\\Projects\\hareesh-portfolio-1\\src\\components\\space\\HelpOverlay.tsx", "source_location": "L1", "weight": 1.0}, {"source": "c_users_myself_desktop_projects_hareesh_portfolio_1_src_components_space_helpoverlay_tsx", "target": "lucide_react", "relation": "imports_from", "confidence": "EXTRACTED", "source_file": "C:\\Users\\myself\\Desktop\\Projects\\hareesh-portfolio-1\\src\\components\\space\\HelpOverlay.tsx", "source_location": "L2", "weight": 1.0}, {"source": "c_users_myself_desktop_projects_hareesh_portfolio_1_src_components_space_helpoverlay_tsx", "target": "c_users_myself_desktop_projects_hareesh_portfolio_1_src_hooks_usefocustrap", "relation": "imports_from", "confidence": "EXTRACTED", "source_file": "C:\\Users\\myself\\Desktop\\Projects\\hareesh-portfolio-1\\src\\components\\space\\HelpOverlay.tsx", "source_location": "L3", "weight": 1.0}, {"source": "c_users_myself_desktop_projects_hareesh_portfolio_1_src_components_space_helpoverlay_tsx", "target": "helpoverlay_helpoverlay", "relation": "contains", "confidence": "EXTRACTED", "source_file": "C:\\Users\\myself\\Desktop\\Projects\\hareesh-portfolio-1\\src\\components\\space\\HelpOverlay.tsx", "source_location": "L19", "weight": 1.0}], "raw_calls": [{"caller_nid": "helpoverlay_helpoverlay", "callee": "useFocusTrap", "source_file": "C:\\Users\\myself\\Desktop\\Projects\\hareesh-portfolio-1\\src\\components\\space\\HelpOverlay.tsx", "source_location": "L20"}, {"caller_nid": "helpoverlay_helpoverlay", "callee": "useEffect", "source_file": "C:\\Users\\myself\\Desktop\\Projects\\hareesh-portfolio-1\\src\\components\\space\\HelpOverlay.tsx", "source_location": "L23"}, {"caller_nid": "helpoverlay_helpoverlay", "callee": "map", "source_file": "C:\\Users\\myself\\Desktop\\Projects\\hareesh-portfolio-1\\src\\components\\space\\HelpOverlay.tsx", "source_location": "L60"}]}